meru/__init__.py
meru/baselines.py
meru/extract_measures.py
meru/multilevel.py
meru/simulate.py
meru/testing.py
pattern_optimized_routes-0.1.6.dist-info/LICENSE
pattern_optimized_routes-0.1.6.dist-info/METADATA
pattern_optimized_routes-0.1.6.dist-info/WHEEL
pattern_optimized_routes-0.1.6.dist-info/top_level.txt
pattern_optimized_routes-0.1.6.dist-info/RECORD
