Metadata-Version: 2.1
Name: pattern-optimized-routes
Version: 0.1.6
Summary: Package to simulate the MultilevelERU (Expected Road Usage) model and the literature baselines results on a road network with a traffic demand.
Home-page: https://github.com/lwdovico/pattern-optimized-routes
Author: Ludovico Lemma
Author-email: lwdovico@protonmail.com
License: MIT
Keywords: Utils
License-File: LICENSE
Requires-Dist: routing-lib
